rahulraifzb/__init__.py
rahulraifzb/app.py
rahulraifzb-0.0.0.dist-info/LICENSE
rahulraifzb-0.0.0.dist-info/METADATA
rahulraifzb-0.0.0.dist-info/WHEEL
rahulraifzb-0.0.0.dist-info/top_level.txt
rahulraifzb-0.0.0.dist-info/RECORD
